{
  "name": "Mephiles",
  "nameDescription": "Mephiles",
  "race": "blood",
  "experience": 415,
  "speed": 300,
  "manaCost": 0,
  "health": {
    "max": 415,
    "now": 415
  },
  "look": {
    "type": 237,
    "head": 0,
    "body": 0,
    "legs": 0,
    "feet": 0,
    "corpse": 10323
  },
  "targetChange": {
    "interval": 5000,
    "chance": 0
  },
  "strategy": {
    "attack": 0,
    "defense": 0
  },
  "flags": {
    "summonable": 0,
    "attackable": 1,
    "hostile": 1,
    "illusionable": 0,
    "convinceable": 0,
    "pushable": 0,
    "canpushitems": 1,
    "canpushcreatures": 1,
    "targetdistance": 3,
    "staticattack": 90,
    "runonhealth": 0,
    "canwalkonenergy": 0,
    "canwalkonpoison": 0
  },
  "attacks": [
    {
      "name": "melee",
      "interval": "1200",
      "min": "0",
      "max": "-35"
    },
    {
      "name": "fire",
      "interval": "1500",
      "chance": "70",
      "range": "7",
      "radius": "2",
      "target": "1",
      "min": "-15",
      "max": "-45",
      "attributes": [
        {
          "shootEffect": "fire"
        },
        {
          "areaEffect": "firearea"
        }
      ]
    }
  ],
  "defense": {
    "armor": 30,
    "defense": 35
  },
  "defenses": [
    {
      "name": "speed",
      "interval": "1000",
      "chance": "40",
      "speedchange": "400",
      "duration": "40000",
      "attributes": [
        {
          "areaEffect": "redshimmer"
        }
      ]
    },
    {
      "name": "invisible",
      "interval": "4000",
      "chance": "50",
      "duration": "5000",
      "attributes": [
        {
          "areaEffect": "redshimmer"
        }
      ]
    }
  ],
  "elements": {
    "earthPercent": 50,
    "icePercent": -10,
    "holyPercent": -5,
    "physicalPercent": -10
  },
  "loot": [],
  "voices": {
    "interval": 5000,
    "chance": 10,
    "sentences": [
      {
        "sentence": "I have a contract here which you should sign!",
        "yell": false
      },
      {
        "sentence": "I sence so much potential in you. It's almost a shame I have to kill you.",
        "yell": false
      },
      {
        "sentence": "Yes, slay me for the loot I might have. Give in to your greed.",
        "yell": false
      },
      {
        "sentence": "Wealth, Power, it is all at your fingertips. All you have to do is a bit blackmailing and bullying.",
        "yell": false
      },
      {
        "sentence": "Come on. being a bit evil won't hurt you.",
        "yell": false
      }
    ]
  },
  "immunities": {
    "fire": 1,
    "lifedrain": 1,
    "drunk": 1,
    "invisible": 1
  },
  "summon": {
    "maxSummons": 0,
    "summons": []
  }
}