{
  "monster": {
    "name": "Inky",
    "nameDescription": "Inky",
    "race": "blood",
    "experience": "250",
    "speed": "520",
    "manacost": "670",
    "health": {
      "now": "600",
      "max": "600"
    },
    "look": {
      "type": "46",
      "corpse": "6065"
    },
    "targetchange": {
      "interval": "5000",
      "chance": "8"
    },
    "flags": {
      "flag": [
        {
          "summonable": "0"
        },
        {
          "attackable": "1"
        },
        {
          "hostile": "1"
        },
        {
          "illusionable": "0"
        },
        {
          "convinceable": "0"
        },
        {
          "pushable": "0"
        },
        {
          "canpushitems": "1"
        },
        {
          "canpushcreatures": "0"
        },
        {
          "staticattack": "90"
        },
        {
          "targetdistance": "1"
        },
        {
          "runonhealth": "0"
        }
      ]
    },
    "attacks": {
      "attack": [
        {
          "name": "melee",
          "interval": "2000",
          "min": "0",
          "max": "-741"
        },
        {
          "name": "lifedrain",
          "interval": "2000",
          "chance": "15",
          "radius": "3",
          "target": "0",
          "max": "-87",
          "attribute": {
            "key": "areaEffect",
            "value": "blackspark"
          }
        },
        {
          "name": "poisonfield",
          "interval": "2000",
          "chance": "19",
          "range": "7",
          "radius": "3",
          "target": "0",
          "attribute": {
            "key": "shootEffect",
            "value": "poison"
          }
        },
        {
          "name": "physical",
          "interval": "2000",
          "chance": "7",
          "range": "7",
          "target": "1",
          "min": "-56",
          "max": "-87",
          "attribute": {
            "key": "shootEffect",
            "value": "snowball"
          }
        },
        {
          "name": "energycondition",
          "interval": "2000",
          "chance": "10",
          "min": "-75",
          "max": "-75",
          "range": "1",
          "target": "1",
          "attribute": {
            "key": "shootEffect",
            "value": "energy"
          }
        }
      ]
    },
    "defenses": {
      "armor": "15",
      "defense": "15"
    },
    "elements": {
      "element": {
        "energyPercent": "-15"
      }
    },
    "immunities": {
      "immunity": [
        {
          "lifedrain": "1"
        },
        {
          "ice": "1"
        },
        {
          "earth": "1"
        }
      ]
    },
    "voices": {
      "interval": "5000",
      "chance": "10",
      "voice": [
        {
          "sentence": "Tssss!"
        },
        {
          "sentence": "Gaaahhh!"
        },
        {
          "sentence": "Gluh! Gluh!"
        },
        {
          "sentence": "Boohaa!"
        }
      ]
    }
  }
}