{
  "name": "Lizard Snakecharmer",
  "nameDescription": "a lizard snakecharmer",
  "race": "blood",
  "experience": 210,
  "speed": 190,
  "manaCost": 0,
  "health": {
    "max": 325,
    "now": 325
  },
  "look": {
    "type": 115,
    "corpse": 6041
  },
  "targetChange": {
    "interval": 4000,
    "chance": 0
  },
  "strategy": {
    "attack": 0,
    "defense": 0
  },
  "flags": {
    "summonable": 0,
    "attackable": 1,
    "hostile": 1,
    "illusionable": 1,
    "convinceable": 0,
    "pushable": 1,
    "canpushitems": 1,
    "canpushcreatures": 0,
    "targetdistance": 4,
    "staticattack": 80,
    "runonhealth": 15,
    "canwalkonenergy": 0,
    "canwalkonfire": 0
  },
  "attacks": [
    {
      "name": "melee",
      "interval": "2000",
      "min": "0",
      "max": "-30"
    },
    {
      "name": "poisoncondition",
      "interval": "2000",
      "chance": "15",
      "range": "7",
      "min": "-100",
      "max": "-200",
      "attributes": [
        {
          "shootEffect": "poison"
        }
      ]
    },
    {
      "name": "earth",
      "interval": "2000",
      "chance": "15",
      "range": "7",
      "radius": "1",
      "target": "1",
      "min": "-50",
      "max": "-110",
      "attributes": [
        {
          "shootEffect": "poison"
        },
        {
          "areaEffect": "greenbubble"
        }
      ]
    }
  ],
  "defense": {
    "armor": 15,
    "defense": 15
  },
  "defenses": [
    {
      "name": "healing",
      "interval": "2000",
      "chance": "50",
      "min": "50",
      "max": "100",
      "attributes": [
        {
          "areaEffect": "blueshimmer"
        }
      ]
    },
    {
      "name": "invisible",
      "interval": "2000",
      "chance": "10",
      "duration": "3000",
      "attributes": [
        {
          "areaEffect": "blueshimmer"
        }
      ]
    }
  ],
  "elements": {
    "energyPercent": 20,
    "icePercent": 20,
    "physicalPercent": -20,
    "firePercent": -10
  },
  "loot": [
    {
      "id": 0,
      "countmax": 55,
      "chance": 83740,
      "items": [],
      "name": "gold coin"
    },
    {
      "id": 0,
      "countmax": 1,
      "chance": 520,
      "items": [],
      "name": "small amethyst"
    },
    {
      "id": 0,
      "countmax": 1,
      "chance": 150,
      "items": [],
      "name": "yellow gem"
    },
    {
      "id": 0,
      "countmax": 1,
      "chance": 340,
      "items": [],
      "name": "life ring"
    },
    {
      "id": 0,
      "countmax": 1,
      "chance": 1430,
      "items": [],
      "name": "life crystal"
    },
    {
      "id": 0,
      "countmax": 1,
      "chance": 920,
      "items": [],
      "name": "terra rod"
    },
    {
      "id": 0,
      "countmax": 1,
      "chance": 230,
      "items": [],
      "name": "snakebite rod"
    },
    {
      "id": 0,
      "countmax": 1,
      "chance": 8640,
      "items": [],
      "name": "cape"
    },
    {
      "id": 3077,
      "countmax": 1,
      "chance": 30000,
      "items": [],
      "name": null
    },
    {
      "id": 0,
      "countmax": 1,
      "chance": 230,
      "items": [],
      "name": "charmer's tiara"
    },
    {
      "id": 0,
      "countmax": 1,
      "chance": 1320,
      "items": [],
      "name": "lizard leather"
    },
    {
      "id": 0,
      "countmax": 1,
      "chance": 860,
      "items": [],
      "name": "lizard scale"
    },
    {
      "id": 0,
      "countmax": 1,
      "chance": 860,
      "items": [],
      "name": "mana potion"
    }
  ],
  "voices": {
    "interval": 5000,
    "chance": 10,
    "sentences": [
      {
        "sentence": "I ssssmell warm blood!",
        "yell": false
      },
      {
        "sentence": "Shhhhhhhh",
        "yell": false
      }
    ]
  },
  "immunities": {
    "invisible": 1,
    "earth": 1
  },
  "summon": {
    "maxSummons": 6,
    "summons": [
      {
        "name": "cobra",
        "interval": 2000,
        "chance": 20,
        "max": 0
      }
    ]
  }
}